hs/__init__.py
hs/cli/__init__.py
hs/cli/commands/__init__.py
hs/cli/commands/app.py
hs/cli/commands/apply.py
hs/cli/commands/cluster.py
hs/cli/commands/deployment_configuration.py
hs/cli/commands/hs.py
hs/cli/commands/model.py
hs/cli/commands/profile.py
hs/cli/commands/servable.py
hs/cli/context.py
hs/cli/help.py
hs/entities/__init__.py
hs/entities/application.py
hs/entities/base_entity.py
hs/entities/cluster_config.py
hs/entities/contract.py
hs/entities/deployment_config.py
hs/entities/model_version.py
hs/metadata_collectors/__init__.py
hs/metadata_collectors/collected_metadata.py
hs/metadata_collectors/dvc.py
hs/metadata_collectors/git.py
hs/metadata_collectors/hs.py
hs/settings.py
hs/util/__init__.py
hs/util/dockerutils.py
hs/util/logutils.py
hs-3.0.3.dist-info/entry_points.txt
hs-3.0.3.dist-info/LICENSE
hs-3.0.3.dist-info/WHEEL
hs-3.0.3.dist-info/METADATA
hs-3.0.3.dist-info/RECORD
